robusta/__init__.py
robusta/batchnorm/__init__.py
robusta/batchnorm/bn.py
robusta/batchnorm/stages.py
robusta/datasets/__init__.py
robusta/datasets/base.py
robusta/datasets/imagenet200.py
robusta/datasets/imageneta.py
robusta/datasets/imagenetc.py
robusta/datasets/imagenetr.py
robusta/models/BiT_models.py
robusta/models/__init__.py
robusta/models/fixup.py
robusta/models/imagenet_model.py
robusta/models/resnet_gn.py
robusta/selflearning/__init__.py
robusta/selflearning/functional.py
robusta/selflearning/nn.py
robusta-0.0.2.dist-info/LICENSE
robusta-0.0.2.dist-info/METADATA
robusta-0.0.2.dist-info/NOTICE
robusta-0.0.2.dist-info/WHEEL
robusta-0.0.2.dist-info/top_level.txt
robusta-0.0.2.dist-info/RECORD
