Metadata-Version: 2.1
Name: robusta
Version: 0.0.2
Summary: A pytorch package for robustness and adaptation research
Home-page: https://github.com/bethgelab/robustness
Author: Evgenia Rusak, Steffen Schneider, George Pachitariu
Author-email: steffen@bethgelab.org
Project-URL: Bug Tracker, https://github.com/bethgelab/robustness/issues
Classifier: Programming Language :: Python :: 3
Classifier: License :: OSI Approved :: Apache Software License
Classifier: Operating System :: OS Independent
Requires-Python: >=3.8
License-File: LICENSE
License-File: NOTICE
Requires-Dist: torch
Requires-Dist: torchvision
Requires-Dist: numpy
Requires-Dist: tqdm
Provides-Extra: dev
Requires-Dist: pytest ; extra == 'dev'
